datasette_edit_templates/__init__.py
datasette_edit_templates/static/cm-resize-1.0.1.min.js
datasette_edit_templates/static/codemirror-5.57.0.min.css
datasette_edit_templates/static/codemirror-5.57.0.min.js
datasette_edit_templates/static/jinja2.js
datasette_edit_templates/templates/edit_template.html
datasette_edit_templates/templates/edit_templates_index.html
datasette_edit_templates-0.4.3.dist-info/METADATA
datasette_edit_templates-0.4.3.dist-info/WHEEL
datasette_edit_templates-0.4.3.dist-info/entry_points.txt
datasette_edit_templates-0.4.3.dist-info/top_level.txt
datasette_edit_templates-0.4.3.dist-info/RECORD
