Metadata-Version: 2.1
Name: datasette-edit-templates
Version: 0.4.3
Summary: Plugin allowing Datasette templates to be edited within Datasette
Home-page: https://github.com/simonw/datasette-edit-templates
Author: Simon Willison
License: Apache License, Version 2.0
Project-URL: Issues, https://github.com/simonw/datasette-edit-templates/issues
Project-URL: CI, https://github.com/simonw/datasette-edit-templates/actions
Project-URL: Changelog, https://github.com/simonw/datasette-edit-templates/releases
Requires-Python: >=3.8
Requires-Dist: datasette >=0.63
Provides-Extra: playwright
Requires-Dist: pytest-playwright ; extra == 'playwright'
Provides-Extra: test
Requires-Dist: pytest ; extra == 'test'
Requires-Dist: pytest-asyncio ; extra == 'test'
Requires-Dist: sqlite-utils ; extra == 'test'
Requires-Dist: datasette-test >=0.2 ; extra == 'test'
Requires-Dist: nest-asyncio ; extra == 'test'
